{
  "items": [
    {
      "name": "Nuxt",
      "link": "https://nuxt.com/",
      "logo": "SvgoNuxtColor"
    },
    {
      "name": "Vue",
      "link": "https://vuejs.org/",
      "logo": "SvgoVueColor"
    },
    {
      "name": "Angular",
      "link": "https://angular.dev/",
      "logo": "SvgoAngularColor"
    },
    {
      "name": "React",
      "link": "https://react.dev/",
      "logo": "SvgoReactColor"
    },
    {
      "name": "Unity",
      "link": "https://unity.com/",
      "logo": "SvgoUnity"
    },
    {
      "name": "Godot",
      "link": "https://godotengine.org/",
      "logo": "SvgoGodotColor"
    }
    
  ]
}
